{
  "collection": "OG Earrings",
  "id": 342,
  "total_issued": 1000,
  "name": "OG Earring #342",
  "dna": "91c06001eaab5b7c22f3f3eb697508f204e5e705",
  "description": "Collection of OG Earrings for your Apes",
  "image": "ipfs://QmZVzDfSWLpccLCMLwqzaASo15PPEmZs6GNTWKMm8Z2Dpt/342.png",
  "date_generation": 1643303787938,
  "date_market": "February 2022",
  "info": [
    "https://apecessories.com",
    "https://apecessories.store"
  ],
  "productionLab": "web4 OG",
  "collectionPath": "earrings",
  "fittingApeCollections": [
    "bayc"
  ],
  "fittingApes": [
    0
  ]
}