{
  "collection": "OG Earrings",
  "id": 44,
  "total_issued": 1000,
  "name": "OG Earring #44",
  "dna": "3eeeb4b479349001e5432fd40d3144d01c610c86",
  "description": "Collection of OG Earrings for your Apes",
  "image": "ipfs://QmZVzDfSWLpccLCMLwqzaASo15PPEmZs6GNTWKMm8Z2Dpt/44.png",
  "date_generation": 1643303763843,
  "date_market": "February 2022",
  "info": [
    "https://apecessories.com",
    "https://apecessories.store"
  ],
  "productionLab": "web4 OG",
  "collectionPath": "earrings",
  "fittingApeCollections": [
    "bayc"
  ],
  "fittingApes": [
    0
  ]
}